tonie_api/__init__.py
tonie_api/api.py
tonie_api/models.py
tonie_api/session.py
tonie_api-0.1.2.dist-info/LICENSE
tonie_api-0.1.2.dist-info/METADATA
tonie_api-0.1.2.dist-info/WHEEL
tonie_api-0.1.2.dist-info/RECORD
