Metadata-Version: 2.1
Name: tonie-api
Version: 0.1.2
Summary: Python library to access the REST API of the toniecloud. NOT associated with Boxine (tonies.de) in any way.
Home-page: https://github.com/Wilhelmsson177/tonie-api
License: MIT
Author: Willi Meierhof
Author-email: willi@meierhof.dev
Requires-Python: >=3.11,<4.0
Classifier: Development Status :: 4 - Beta
Classifier: Intended Audience :: Developers
Classifier: License :: OSI Approved :: MIT License
Classifier: Natural Language :: English
Classifier: Operating System :: OS Independent
Classifier: Programming Language :: Python :: 3
Classifier: Programming Language :: Python :: 3.11
Classifier: Programming Language :: Python :: 3.12
Classifier: Programming Language :: Python :: 3.13
Classifier: Topic :: Software Development :: Libraries
Requires-Dist: pydantic (>=2.3.0,<3.0.0)
Requires-Dist: requests-oauthlib (>=1.3.1,<2.0.0)
Project-URL: Bug Tracker, https://github.com/Wilhelmsson177/tonie-api/issues
Project-URL: Changelog, https://github.com/Wilhelmsson177/tonie-api/blob/main/CHANGELOG.md
Project-URL: Documentation, https://tonie-api.readthedocs.io
Project-URL: Repository, https://github.com/Wilhelmsson177/tonie-api
